{"success":true,"data":{"generated_at":"2026-07-17T02:45:05.533290Z","universe_size":18,"evaluated_count":18,"candidates":[{"code":"000037","name":"深南电A","total_score":74.49,"coverage_ratio":0.675,"risk_level":"medium","reasons":["技术规则分 90","强势归因：电力+储能+综合能源服务+中报扭亏"],"evidence_updated_at":"2026-07-17T02:45:11.075699Z","latest_price":9.2,"change_percent":10.05,"pe_ttm":29.92,"pb":3.32,"total_market_cap_yi":31.18,"industry":"电力","opportunity_type":"trend","strategy_title":"趋势观察","strategy_summary":"价格位于 MA20 上方且 MACD 柱为正。","support":7.88,"resistance":10.39,"volume_ratio_5d":1.8386786007301086,"capital_summary":"已采集 90 日资金流。","catalysts":["强势归因：电力+储能+综合能源服务+中报扭亏"],"risks":[],"concept_tags":["电力","储能","综合能源服务","中报扭亏"],"evidence_sources":["腾讯财经复权日线","腾讯财经实时行情","同花顺强势股题材归因","东方财富个股资金流"],"data_gaps":["补齐公告、解禁、质押和个股新闻语义证据。"],"components":[{"key":"technical","name":"技术面","score":90.0,"coverage_ratio":1.0},{"key":"capital_flow","name":"资金面","score":55.0,"coverage_ratio":0.6},{"key":"fundamental","name":"基本面","score":68.0,"coverage_ratio":0.55},{"key":"industry","name":"行业景气","score":65.0,"coverage_ratio":0.6},{"key":"news_sentiment","name":"公告与新闻","score":55.0,"coverage_ratio":0.3},{"key":"risk_control","name":"风险控制","score":80.0,"coverage_ratio":0.5}]},{"code":"601369","name":"陕鼓动力","total_score":74.49,"coverage_ratio":0.675,"risk_level":"medium","reasons":["技术规则分 90","强势归因：压缩空气储能+资产重组+西安国资"],"evidence_updated_at":"2026-07-17T02:45:14.771587Z","latest_price":9.5,"change_percent":9.95,"pe_ttm":23.66,"pb":1.85,"total_market_cap_yi":162.09,"industry":"压缩空气储能","opportunity_type":"trend","strategy_title":"趋势观察","strategy_summary":"价格位于 MA20 上方且 MACD 柱为正。","support":8.13,"resistance":9.96,"volume_ratio_5d":0.8632944934898182,"capital_summary":"已采集 90 日资金流。","catalysts":["强势归因：压缩空气储能+资产重组+西安国资"],"risks":[],"concept_tags":["压缩空气储能","资产重组","西安国资"],"evidence_sources":["腾讯财经复权日线","腾讯财经实时行情","同花顺强势股题材归因","东方财富个股资金流"],"data_gaps":["补齐公告、解禁、质押和个股新闻语义证据。"],"components":[{"key":"technical","name":"技术面","score":90.0,"coverage_ratio":1.0},{"key":"capital_flow","name":"资金面","score":55.0,"coverage_ratio":0.6},{"key":"fundamental","name":"基本面","score":68.0,"coverage_ratio":0.55},{"key":"industry","name":"行业景气","score":65.0,"coverage_ratio":0.6},{"key":"news_sentiment","name":"公告与新闻","score":55.0,"coverage_ratio":0.3},{"key":"risk_control","name":"风险控制","score":80.0,"coverage_ratio":0.5}]},{"code":"600095","name":"湘财股份","total_score":72.86,"coverage_ratio":0.675,"risk_level":"medium","reasons":["技术规则分 90","强势归因：中报预增+吸收合并+证券"],"evidence_updated_at":"2026-07-17T02:45:07.770478Z","latest_price":8.69,"change_percent":10.0,"pe_ttm":56.59,"pb":2.02,"total_market_cap_yi":248.46,"industry":"中报预增","opportunity_type":"observe","strategy_title":"接近压力，避免追高","strategy_summary":"价格接近 20 日压力位，等待突破或回踩。","support":7.2,"resistance":8.69,"volume_ratio_5d":1.5087397720011921,"capital_summary":"已采集 90 日资金流。","catalysts":["强势归因：中报预增+吸收合并+证券"],"risks":[],"concept_tags":["中报预增","吸收合并","证券"],"evidence_sources":["腾讯财经复权日线","腾讯财经实时行情","同花顺强势股题材归因","东方财富个股资金流"],"data_gaps":["补齐公告、解禁、质押和个股新闻语义证据。"],"components":[{"key":"technical","name":"技术面","score":90.0,"coverage_ratio":1.0},{"key":"capital_flow","name":"资金面","score":55.0,"coverage_ratio":0.6},{"key":"fundamental","name":"基本面","score":58.0,"coverage_ratio":0.55},{"key":"industry","name":"行业景气","score":65.0,"coverage_ratio":0.6},{"key":"news_sentiment","name":"公告与新闻","score":55.0,"coverage_ratio":0.3},{"key":"risk_control","name":"风险控制","score":80.0,"coverage_ratio":0.5}]},{"code":"603118","name":"共进股份","total_score":71.56,"coverage_ratio":0.675,"risk_level":"medium","reasons":["技术规则分 90","强势归因：数据中心交换机+机器人+国企改革+回购"],"evidence_updated_at":"2026-07-17T02:45:12.981869Z","latest_price":14.95,"change_percent":10.01,"pe_ttm":147.24,"pb":2.33,"total_market_cap_yi":117.7,"industry":"数据中心交换机","opportunity_type":"observe","strategy_title":"接近压力，避免追高","strategy_summary":"价格接近 20 日压力位，等待突破或回踩。","support":10.7,"resistance":14.98,"volume_ratio_5d":0.7734235268074797,"capital_summary":"已采集 90 日资金流。","catalysts":["强势归因：数据中心交换机+机器人+国企改革+回购"],"risks":[],"concept_tags":["数据中心交换机","机器人","国企改革","回购"],"evidence_sources":["腾讯财经复权日线","腾讯财经实时行情","同花顺强势股题材归因","东方财富个股资金流"],"data_gaps":["补齐公告、解禁、质押和个股新闻语义证据。"],"components":[{"key":"technical","name":"技术面","score":90.0,"coverage_ratio":1.0},{"key":"capital_flow","name":"资金面","score":55.0,"coverage_ratio":0.6},{"key":"fundamental","name":"基本面","score":50.0,"coverage_ratio":0.55},{"key":"industry","name":"行业景气","score":65.0,"coverage_ratio":0.6},{"key":"news_sentiment","name":"公告与新闻","score":55.0,"coverage_ratio":0.3},{"key":"risk_control","name":"风险控制","score":80.0,"coverage_ratio":0.5}]},{"code":"600644","name":"乐山电力","total_score":71.56,"coverage_ratio":0.675,"risk_level":"medium","reasons":["技术规则分 90","强势归因：电力+天然气+新型储能"],"evidence_updated_at":"2026-07-17T02:45:15.392198Z","latest_price":9.01,"change_percent":10.01,"pe_ttm":229.01,"pb":2.53,"total_market_cap_yi":48.51,"industry":"电力","opportunity_type":"observe","strategy_title":"接近压力，避免追高","strategy_summary":"价格接近 20 日压力位，等待突破或回踩。","support":7.51,"resistance":9.225,"volume_ratio_5d":1.937106597239944,"capital_summary":"已采集 90 日资金流。","catalysts":["强势归因：电力+天然气+新型储能"],"risks":[],"concept_tags":["电力","天然气","新型储能"],"evidence_sources":["腾讯财经复权日线","腾讯财经实时行情","同花顺强势股题材归因","东方财富个股资金流"],"data_gaps":["补齐公告、解禁、质押和个股新闻语义证据。"],"components":[{"key":"technical","name":"技术面","score":90.0,"coverage_ratio":1.0},{"key":"capital_flow","name":"资金面","score":55.0,"coverage_ratio":0.6},{"key":"fundamental","name":"基本面","score":50.0,"coverage_ratio":0.55},{"key":"industry","name":"行业景气","score":65.0,"coverage_ratio":0.6},{"key":"news_sentiment","name":"公告与新闻","score":55.0,"coverage_ratio":0.3},{"key":"risk_control","name":"风险控制","score":80.0,"coverage_ratio":0.5}]},{"code":"600992","name":"贵绳股份","total_score":71.56,"coverage_ratio":0.675,"risk_level":"medium","reasons":["技术规则分 90","强势归因：商业航天+钢丝绳+贵州国资"],"evidence_updated_at":"2026-07-17T02:45:18.274430Z","latest_price":11.72,"change_percent":10.05,"pe_ttm":-976.16,"pb":2.01,"total_market_cap_yi":28.72,"industry":"商业航天","opportunity_type":"observe","strategy_title":"接近压力，避免追高","strategy_summary":"价格接近 20 日压力位，等待突破或回踩。","support":8.36,"resistance":11.72,"volume_ratio_5d":0.685087336984883,"capital_summary":"已采集 90 日资金流。","catalysts":["强势归因：商业航天+钢丝绳+贵州国资"],"risks":[],"concept_tags":["商业航天","钢丝绳","贵州国资"],"evidence_sources":["腾讯财经复权日线","腾讯财经实时行情","同花顺强势股题材归因","东方财富个股资金流"],"data_gaps":["补齐公告、解禁、质押和个股新闻语义证据。"],"components":[{"key":"technical","name":"技术面","score":90.0,"coverage_ratio":1.0},{"key":"capital_flow","name":"资金面","score":55.0,"coverage_ratio":0.6},{"key":"fundamental","name":"基本面","score":50.0,"coverage_ratio":0.55},{"key":"industry","name":"行业景气","score":65.0,"coverage_ratio":0.6},{"key":"news_sentiment","name":"公告与新闻","score":55.0,"coverage_ratio":0.3},{"key":"risk_control","name":"风险控制","score":80.0,"coverage_ratio":0.5}]},{"code":"002766","name":"索菱股份","total_score":71.56,"coverage_ratio":0.675,"risk_level":"medium","reasons":["技术规则分 90","强势归因：车路云+智能座舱+北美市场"],"evidence_updated_at":"2026-07-17T02:45:34.839056Z","latest_price":3.94,"change_percent":10.06,"pe_ttm":-45.59,"pb":3.21,"total_market_cap_yi":33.76,"industry":"车路云","opportunity_type":"observe","strategy_title":"接近压力，避免追高","strategy_summary":"价格接近 20 日压力位，等待突破或回踩。","support":3.3,"resistance":3.95,"volume_ratio_5d":0.9197710341781715,"capital_summary":"已采集 90 日资金流。","catalysts":["强势归因：车路云+智能座舱+北美市场"],"risks":[],"concept_tags":["车路云","智能座舱","北美市场"],"evidence_sources":["腾讯财经复权日线","腾讯财经实时行情","同花顺强势股题材归因","东方财富个股资金流"],"data_gaps":["补齐公告、解禁、质押和个股新闻语义证据。"],"components":[{"key":"technical","name":"技术面","score":90.0,"coverage_ratio":1.0},{"key":"capital_flow","name":"资金面","score":55.0,"coverage_ratio":0.6},{"key":"fundamental","name":"基本面","score":50.0,"coverage_ratio":0.55},{"key":"industry","name":"行业景气","score":65.0,"coverage_ratio":0.6},{"key":"news_sentiment","name":"公告与新闻","score":55.0,"coverage_ratio":0.3},{"key":"risk_control","name":"风险控制","score":80.0,"coverage_ratio":0.5}]},{"code":"600722","name":"金牛化工","total_score":70.25,"coverage_ratio":0.675,"risk_level":"medium","reasons":["技术规则分 90","强势归因：甲醇+风电+河北国资"],"evidence_updated_at":"2026-07-17T02:45:18.892688Z","latest_price":8.53,"change_percent":10.06,"pe_ttm":122.0,"pb":4.6,"total_market_cap_yi":58.03,"industry":"甲醇","opportunity_type":"trend","strategy_title":"趋势观察","strategy_summary":"价格位于 MA20 上方且 MACD 柱为正。","support":7.43,"resistance":9.67,"volume_ratio_5d":0.8016854130365272,"capital_summary":"已采集 90 日资金流。","catalysts":["强势归因：甲醇+风电+河北国资"],"risks":[],"concept_tags":["甲醇","风电","河北国资"],"evidence_sources":["腾讯财经复权日线","腾讯财经实时行情","同花顺强势股题材归因","东方财富个股资金流"],"data_gaps":["补齐公告、解禁、质押和个股新闻语义证据。"],"components":[{"key":"technical","name":"技术面","score":90.0,"coverage_ratio":1.0},{"key":"capital_flow","name":"资金面","score":55.0,"coverage_ratio":0.6},{"key":"fundamental","name":"基本面","score":42.0,"coverage_ratio":0.55},{"key":"industry","name":"行业景气","score":65.0,"coverage_ratio":0.6},{"key":"news_sentiment","name":"公告与新闻","score":55.0,"coverage_ratio":0.3},{"key":"risk_control","name":"风险控制","score":80.0,"coverage_ratio":0.5}]},{"code":"605011","name":"杭州热电","total_score":68.41,"coverage_ratio":0.675,"risk_level":"medium","reasons":["技术规则分 80","强势归因：热电联产+绿色能源+国企改革"],"evidence_updated_at":"2026-07-17T02:45:09.455846Z","latest_price":18.48,"change_percent":10.0,"pe_ttm":38.88,"pb":3.04,"total_market_cap_yi":73.94,"industry":"热电联产","opportunity_type":"observe","strategy_title":"接近压力，避免追高","strategy_summary":"价格接近 20 日压力位，等待突破或回踩。","support":15.11,"resistance":18.48,"volume_ratio_5d":1.9211011570174237,"capital_summary":"已采集 90 日资金流。","catalysts":["强势归因：热电联产+绿色能源+国企改革"],"risks":[],"concept_tags":["热电联产","绿色能源","国企改革"],"evidence_sources":["腾讯财经复权日线","腾讯财经实时行情","同花顺强势股题材归因","东方财富个股资金流"],"data_gaps":["补齐公告、解禁、质押和个股新闻语义证据。"],"components":[{"key":"technical","name":"技术面","score":80.0,"coverage_ratio":1.0},{"key":"capital_flow","name":"资金面","score":55.0,"coverage_ratio":0.6},{"key":"fundamental","name":"基本面","score":58.0,"coverage_ratio":0.55},{"key":"industry","name":"行业景气","score":65.0,"coverage_ratio":0.6},{"key":"news_sentiment","name":"公告与新闻","score":55.0,"coverage_ratio":0.3},{"key":"risk_control","name":"风险控制","score":80.0,"coverage_ratio":0.5}]},{"code":"001258","name":"立新能源","total_score":68.41,"coverage_ratio":0.675,"risk_level":"medium","reasons":["技术规则分 80","强势归因：风电光伏+定增获批+半年报预增+新疆国资"],"evidence_updated_at":"2026-07-17T02:45:15.997121Z","latest_price":8.27,"change_percent":9.97,"pe_ttm":76.59,"pb":2.55,"total_market_cap_yi":77.19,"industry":"风电光伏","opportunity_type":"observe","strategy_title":"接近压力，避免追高","strategy_summary":"价格接近 20 日压力位，等待突破或回踩。","support":6.37,"resistance":8.27,"volume_ratio_5d":1.6789980411072953,"capital_summary":"已采集 90 日资金流。","catalysts":["强势归因：风电光伏+定增获批+半年报预增+新疆国资"],"risks":[],"concept_tags":["风电光伏","定增获批","半年报预增","新疆国资"],"evidence_sources":["腾讯财经复权日线","腾讯财经实时行情","同花顺强势股题材归因","东方财富个股资金流"],"data_gaps":["补齐公告、解禁、质押和个股新闻语义证据。"],"components":[{"key":"technical","name":"技术面","score":80.0,"coverage_ratio":1.0},{"key":"capital_flow","name":"资金面","score":55.0,"coverage_ratio":0.6},{"key":"fundamental","name":"基本面","score":58.0,"coverage_ratio":0.55},{"key":"industry","name":"行业景气","score":65.0,"coverage_ratio":0.6},{"key":"news_sentiment","name":"公告与新闻","score":55.0,"coverage_ratio":0.3},{"key":"risk_control","name":"风险控制","score":80.0,"coverage_ratio":0.5}]},{"code":"001388","name":"信通电子","total_score":67.11,"coverage_ratio":0.675,"risk_level":"medium","reasons":["技术规则分 80","强势归因：电力智能运维+算力租赁+防冰机器人+高送转"],"evidence_updated_at":"2026-07-17T02:45:11.817295Z","latest_price":24.74,"change_percent":10.0,"pe_ttm":49.36,"pb":4.12,"total_market_cap_yi":30.95,"industry":"电力智能运维","opportunity_type":"observe","strategy_title":"接近压力，避免追高","strategy_summary":"价格接近 20 日压力位，等待突破或回踩。","support":16.635,"resistance":24.74,"volume_ratio_5d":1.766370030435286,"capital_summary":"已采集 90 日资金流。","catalysts":["强势归因：电力智能运维+算力租赁+防冰机器人+高送转"],"risks":[],"concept_tags":["电力智能运维","算力租赁","防冰机器人","高送转"],"evidence_sources":["腾讯财经复权日线","腾讯财经实时行情","同花顺强势股题材归因","东方财富个股资金流"],"data_gaps":["补齐公告、解禁、质押和个股新闻语义证据。"],"components":[{"key":"technical","name":"技术面","score":80.0,"coverage_ratio":1.0},{"key":"capital_flow","name":"资金面","score":55.0,"coverage_ratio":0.6},{"key":"fundamental","name":"基本面","score":50.0,"coverage_ratio":0.55},{"key":"industry","name":"行业景气","score":65.0,"coverage_ratio":0.6},{"key":"news_sentiment","name":"公告与新闻","score":55.0,"coverage_ratio":0.3},{"key":"risk_control","name":"风险控制","score":80.0,"coverage_ratio":0.5}]},{"code":"600236","name":"桂冠电力","total_score":64.3,"coverage_ratio":0.675,"risk_level":"medium","reasons":["技术规则分 70","强势归因：水电高增+绿色电力+央企"],"evidence_updated_at":"2026-07-17T02:45:08.591937Z","latest_price":10.62,"change_percent":10.05,"pe_ttm":23.28,"pb":4.87,"total_market_cap_yi":837.11,"industry":"水电高增","opportunity_type":"observe","strategy_title":"接近压力，避免追高","strategy_summary":"价格接近 20 日压力位，等待突破或回踩。","support":8.65,"resistance":10.62,"volume_ratio_5d":1.4309313573284153,"capital_summary":"已采集 90 日资金流。","catalysts":["强势归因：水电高增+绿色电力+央企"],"risks":[],"concept_tags":["水电高增","绿色电力","央企"],"evidence_sources":["腾讯财经复权日线","腾讯财经实时行情","同花顺强势股题材归因","东方财富个股资金流"],"data_gaps":["补齐公告、解禁、质押和个股新闻语义证据。"],"components":[{"key":"technical","name":"技术面","score":70.0,"coverage_ratio":1.0},{"key":"capital_flow","name":"资金面","score":55.0,"coverage_ratio":0.6},{"key":"fundamental","name":"基本面","score":60.0,"coverage_ratio":0.55},{"key":"industry","name":"行业景气","score":65.0,"coverage_ratio":0.6},{"key":"news_sentiment","name":"公告与新闻","score":55.0,"coverage_ratio":0.3},{"key":"risk_control","name":"风险控制","score":80.0,"coverage_ratio":0.5}]},{"code":"603120","name":"肯特催化","total_score":60.44,"coverage_ratio":0.675,"risk_level":"medium","reasons":["技术规则分 65","强势归因：光刻胶+季铵化合物+电子化学品"],"evidence_updated_at":"2026-07-17T02:45:10.471683Z","latest_price":56.66,"change_percent":10.0,"pe_ttm":60.8,"pb":4.3,"total_market_cap_yi":21.47,"industry":"光刻胶","opportunity_type":"pullback","strategy_title":"回踩观察","strategy_summary":"等待价格在支撑和 MA20 附近形成新证据。","support":46.88,"resistance":63.5,"volume_ratio_5d":0.9396088774831289,"capital_summary":"已采集 90 日资金流。","catalysts":["强势归因：光刻胶+季铵化合物+电子化学品"],"risks":[],"concept_tags":["光刻胶","季铵化合物","电子化学品"],"evidence_sources":["腾讯财经复权日线","腾讯财经实时行情","同花顺强势股题材归因","东方财富个股资金流"],"data_gaps":["补齐公告、解禁、质押和个股新闻语义证据。"],"components":[{"key":"technical","name":"技术面","score":65.0,"coverage_ratio":1.0},{"key":"capital_flow","name":"资金面","score":55.0,"coverage_ratio":0.6},{"key":"fundamental","name":"基本面","score":50.0,"coverage_ratio":0.55},{"key":"industry","name":"行业景气","score":65.0,"coverage_ratio":0.6},{"key":"news_sentiment","name":"公告与新闻","score":55.0,"coverage_ratio":0.3},{"key":"risk_control","name":"风险控制","score":80.0,"coverage_ratio":0.5}]},{"code":"600744","name":"华银电力","total_score":54.7,"coverage_ratio":0.675,"risk_level":"medium","reasons":["技术规则分 55","强势归因：火电+新能源+定增获批+央企"],"evidence_updated_at":"2026-07-17T02:45:17.665692Z","latest_price":5.96,"change_percent":9.96,"pe_ttm":83.87,"pb":9.39,"total_market_cap_yi":121.06,"industry":"火电","opportunity_type":"pullback","strategy_title":"回踩观察","strategy_summary":"等待价格在支撑和 MA20 附近形成新证据。","support":5.22,"resistance":7.27,"volume_ratio_5d":1.3693365758214493,"capital_summary":"已采集 90 日资金流。","catalysts":["强势归因：火电+新能源+定增获批+央企"],"risks":[],"concept_tags":["火电","新能源","定增获批","央企"],"evidence_sources":["腾讯财经复权日线","腾讯财经实时行情","同花顺强势股题材归因","东方财富个股资金流"],"data_gaps":["补齐公告、解禁、质押和个股新闻语义证据。"],"components":[{"key":"technical","name":"技术面","score":55.0,"coverage_ratio":1.0},{"key":"capital_flow","name":"资金面","score":55.0,"coverage_ratio":0.6},{"key":"fundamental","name":"基本面","score":42.0,"coverage_ratio":0.55},{"key":"industry","name":"行业景气","score":65.0,"coverage_ratio":0.6},{"key":"news_sentiment","name":"公告与新闻","score":55.0,"coverage_ratio":0.3},{"key":"risk_control","name":"风险控制","score":80.0,"coverage_ratio":0.5}]}],"status":"available","message":"GitHub Actions 云端候选池；仅使用本次成功采集的真实字段。","disclaimer":"候选为研究筛选，不构成买卖建议，不保证收益。"},"message":"cloud selection loaded"}